tensor2tensor/__init__.py
tensor2tensor/problems.py
tensor2tensor/problems_test.py
tensor2tensor/bin/__init__.py
tensor2tensor/bin/build_vocab.py
tensor2tensor/bin/make_tf_configs.py
tensor2tensor/bin/t2t_attack.py
tensor2tensor/bin/t2t_avg_all.py
tensor2tensor/bin/t2t_bleu.py
tensor2tensor/bin/t2t_datagen.py
tensor2tensor/bin/t2t_decoder.py
tensor2tensor/bin/t2t_distill.py
tensor2tensor/bin/t2t_eval.py
tensor2tensor/bin/t2t_prune.py
tensor2tensor/bin/t2t_trainer.py
tensor2tensor/bin/t2t_trainer_test.py
tensor2tensor/bin/t2t_translate_all.py
tensor2tensor/data_generators/__init__.py
tensor2tensor/data_generators/algorithmic.py
tensor2tensor/data_generators/algorithmic_math.py
tensor2tensor/data_generators/algorithmic_math_test.py
tensor2tensor/data_generators/algorithmic_test.py
tensor2tensor/data_generators/all_problems.py
tensor2tensor/data_generators/allen_brain.py
tensor2tensor/data_generators/allen_brain_test.py
tensor2tensor/data_generators/audio.py
tensor2tensor/data_generators/audio_encoder.py
tensor2tensor/data_generators/audio_test.py
tensor2tensor/data_generators/babi_qa.py
tensor2tensor/data_generators/bair_robot_pushing.py
tensor2tensor/data_generators/celeba.py
tensor2tensor/data_generators/celeba_test.py
tensor2tensor/data_generators/celebahq.py
tensor2tensor/data_generators/cifar.py
tensor2tensor/data_generators/cipher.py
tensor2tensor/data_generators/cnn_dailymail.py
tensor2tensor/data_generators/cola.py
tensor2tensor/data_generators/common_voice.py
tensor2tensor/data_generators/common_voice_test.py
tensor2tensor/data_generators/conll_ner.py
tensor2tensor/data_generators/deepspeech.py
tensor2tensor/data_generators/desc2code.py
tensor2tensor/data_generators/desc2code_test.py
tensor2tensor/data_generators/dna_encoder.py
tensor2tensor/data_generators/dna_encoder_test.py
tensor2tensor/data_generators/fsns.py
tensor2tensor/data_generators/function_docstring.py
tensor2tensorManuel-0.2.dist-info/DESCRIPTION.rst
tensor2tensorManuel-0.2.dist-info/METADATA
tensor2tensorManuel-0.2.dist-info/RECORD
tensor2tensorManuel-0.2.dist-info/WHEEL
tensor2tensorManuel-0.2.dist-info/dependency_links.txt
tensor2tensorManuel-0.2.dist-info/metadata.json
tensor2tensorManuel-0.2.dist-info/top_level.txt
